pip_plus/__init__.py
pip_plus/core.py
pip_plus/pip_plus.py
pip_plus/controllor/ProcessGET.py
pip_plus/html/index.html
pip_plus/html/css/baseStyle.css
pip_plus/html/css/bootstrap-min.css
pip_plus/html/css/bootstrap.min.css
pip_plus/html/css/bootstrap.min.css.map
pip_plus/html/css/dashboard.css
pip_plus/html/css/fileinput.min.css
pip_plus/html/css/jquery.loading.css
pip_plus/html/css/jquery.loading.min.css
pip_plus/html/images/favicon.ico
pip_plus/html/images/white-cube.svg
pip_plus/html/scripts/bootstrap.js
pip_plus/html/scripts/dataHandleScript.js
pip_plus/html/scripts/fileinput.min.js
pip_plus/html/scripts/ie10-viewport-bug-workaround.js
pip_plus/html/scripts/jquery-3.2.1.min.js
pip_plus/html/scripts/jquery-3.3.1.min.js
pip_plus/html/scripts/jquery.loading.js
pip_plus/html/scripts/jquery.loading.min.js
pip_plus/html/scripts/layoutScript.js
pip_plus/html/scripts/mainScript.js
pip_plus/html/scripts/pageHandleScript.js
pip_plus/html/scripts/popper.min.js
pip_plus-0.0.1.dev4.dist-info/LICENSE.txt
pip_plus-0.0.1.dev4.dist-info/METADATA
pip_plus-0.0.1.dev4.dist-info/RECORD
pip_plus-0.0.1.dev4.dist-info/WHEEL
pip_plus-0.0.1.dev4.dist-info/entry_points.txt
pip_plus-0.0.1.dev4.dist-info/top_level.txt
