Metadata-Version: 2.1
Name: pip-plus
Version: 0.0.1.dev4
Summary: A small pip web management tool package
Home-page: https://github.com/hmhuo/pip-plus
Author: huohongming
Author-email: gin_huo@hotmail.com
License: MIT
Project-URL: Documentation, https://github.com/hmhuo/pip-plus/wiki
Project-URL: Source, https://github.com/hmhuo/pip-plus
Project-URL: Tracker, https://github.com/hmhuo/pip-plus/issues
Keywords: sample setuptools development
Platform: windows
Classifier: Development Status :: 2 - Pre-Alpha
Classifier: Environment :: Console
Classifier: Environment :: Web Environment
Classifier: Programming Language :: Python
Classifier: Programming Language :: Python :: 3
Classifier: Programming Language :: Python :: 3.4
Classifier: Programming Language :: Python :: 3.5
Classifier: Programming Language :: Python :: 3.6
Requires-Python: >=3.4
